RagnarokEngine3
