Metadata-Version: 1.2
Name: RagnarokEngine3
Version: 1.0.0a11
Summary: Simple and easy 2D game engine for pygame applications
Home-page: https://github.com/Scoppio/RagnarokEngine3
Author: Lucas Scoppio
Author-email: lucascoppio@gmail.com
License: LGPL 3
Keywords: pygame python3 engine game
Platform: UNKNOWN
Classifier: Development Status :: 3 - Alpha
Classifier: Intended Audience :: Developers
Classifier: Topic :: Software Development :: Libraries :: pygame
Classifier: License :: OSI Approved :: GNU Lesser General Public License v3 or later (LGPLv3+)
Classifier: Programming Language :: Python :: 3 :: Only
Classifier: Programming Language :: Python :: 3.6
Classifier: Programming Language :: Python :: 3.7
Requires-Python: >=3.6.*, <4
